rclone_ls.py
rclone_ls-0.0.2.dist-info/LICENSE
rclone_ls-0.0.2.dist-info/METADATA
rclone_ls-0.0.2.dist-info/WHEEL
rclone_ls-0.0.2.dist-info/entry_points.txt
rclone_ls-0.0.2.dist-info/top_level.txt
rclone_ls-0.0.2.dist-info/RECORD
