Metadata-Version: 2.1
Name: rclone-ls
Version: 0.0.2
Summary: Script to list files/dirs and their sizes in a given rclone path.
Home-page: https://github.com/dportabella/rclone_ls
Author: David Portabella
Author-email: david.portabella@gmail.com
License: MIT
Keywords: Python,rclone,ls
Requires-Python: >=3.0
License-File: LICENSE
Requires-Dist: rclone (>=0.4.4)
Requires-Dist: humanize (>=4.6.0)
